Metadata-Version: 2.1
Name: binarycalculation
Version: 1.5
Summary: Binary Number Calculations
Author: Josi Kie N.
Author-email: kiejosi12@gmail.com
